sphinx_openapi/.idea/.gitignore
sphinx_openapi/.idea/CustomInspectionsConfig.xml
sphinx_openapi/.idea/inspectionProfiles/profiles_settings.xml
sphinx_openapi/.idea/inspectionProfiles/Project_Default.xml
sphinx_openapi/.idea/misc.xml
sphinx_openapi/.idea/modules.xml
sphinx_openapi/.idea/sphinx_openapi.iml
sphinx_openapi/.idea/vcs.xml
sphinx_openapi/__init__.py
sphinx_openapi/cli.py
sphinx_openapi/models/schema_info.py
sphinx_openapi/sphinx_openapi.py
sphinx_openapi-1.0.10.dist-info/LICENSE
sphinx_openapi-1.0.10.dist-info/METADATA
sphinx_openapi-1.0.10.dist-info/WHEEL
sphinx_openapi-1.0.10.dist-info/RECORD
