Metadata-Version: 2.3
Name: sphinx_openapi
Version: 1.0.10
Summary: Sphinx extension for OpenAPI documentation
License: MIT
Author: Xsolla Backend
Author-email: xbe@xsolla.com
Requires-Python: >=3.10
Classifier: Framework :: Sphinx :: Extension
Classifier: Intended Audience :: Developers
Classifier: License :: OSI Approved :: MIT License
Classifier: Operating System :: OS Independent
Classifier: Programming Language :: Python :: 3
Classifier: Programming Language :: Python :: 3.10
Classifier: Programming Language :: Python :: 3.11
Classifier: Programming Language :: Python :: 3.12
Classifier: Programming Language :: Python :: 3.13
Classifier: Topic :: Software Development :: Build Tools
Classifier: Topic :: Software Development :: Documentation
Requires-Dist: orjson (>=3.10.7)
Requires-Dist: pyyaml (>=6.0.1)
Requires-Dist: requests (>=2.32.3)
Requires-Dist: sphinx (>=7.3.7)
Requires-Dist: sphinxcontrib-redoc (==1.6.0)
Project-URL: Homepage, https://github.com/Unidocs1/sphinx_openapi
Project-URL: Issues, https://github.com/Unidocs1/sphinx_openapi/issues
